Metadata-Version: 2.1
Name: chthonic
Version: 0.0.0
Summary: A boilerplate environment for Python package development.
Home-page: https://github.com/crainiac/chthonic
Author: Alex Crain
Author-email: alex@crain.xyz
License: MIT
Platform: UNKNOWN
Classifier: Programming Language :: Python :: 3
Classifier: License :: OSI Approved :: MIT License
Classifier: Operating System :: OS Independent
